odoo8_addon_l10n_ch_dta-8.0.1.0.1.99.dev20-py2.7-nspkg.pth
odoo8_addon_l10n_ch_dta-8.0.1.0.1.99.dev20.dist-info/DESCRIPTION.rst
odoo8_addon_l10n_ch_dta-8.0.1.0.1.99.dev20.dist-info/METADATA
odoo8_addon_l10n_ch_dta-8.0.1.0.1.99.dev20.dist-info/RECORD
odoo8_addon_l10n_ch_dta-8.0.1.0.1.99.dev20.dist-info/WHEEL
odoo8_addon_l10n_ch_dta-8.0.1.0.1.99.dev20.dist-info/metadata.json
odoo8_addon_l10n_ch_dta-8.0.1.0.1.99.dev20.dist-info/namespace_packages.txt
odoo8_addon_l10n_ch_dta-8.0.1.0.1.99.dev20.dist-info/top_level.txt
odoo_addons/l10n_ch_dta/__init__.py
odoo_addons/l10n_ch_dta/__openerp__.py
odoo_addons/l10n_ch_dta/bank.py
odoo_addons/l10n_ch_dta/bank_view.xml
odoo_addons/l10n_ch_dta/payment.py
odoo_addons/l10n_ch_dta/demo/dta_demo.xml
odoo_addons/l10n_ch_dta/i18n/am.po
odoo_addons/l10n_ch_dta/i18n/ar.po
odoo_addons/l10n_ch_dta/i18n/bg.po
odoo_addons/l10n_ch_dta/i18n/bs.po
odoo_addons/l10n_ch_dta/i18n/ca.po
odoo_addons/l10n_ch_dta/i18n/ca_ES.po
odoo_addons/l10n_ch_dta/i18n/cs.po
odoo_addons/l10n_ch_dta/i18n/da.po
odoo_addons/l10n_ch_dta/i18n/de.po
odoo_addons/l10n_ch_dta/i18n/el_GR.po
odoo_addons/l10n_ch_dta/i18n/en_AU.po
odoo_addons/l10n_ch_dta/i18n/en_GB.po
odoo_addons/l10n_ch_dta/i18n/es.po
odoo_addons/l10n_ch_dta/i18n/es_AR.po
odoo_addons/l10n_ch_dta/i18n/es_CL.po
odoo_addons/l10n_ch_dta/i18n/es_CO.po
odoo_addons/l10n_ch_dta/i18n/es_CR.po
odoo_addons/l10n_ch_dta/i18n/es_DO.po
odoo_addons/l10n_ch_dta/i18n/es_EC.po
odoo_addons/l10n_ch_dta/i18n/es_MX.po
odoo_addons/l10n_ch_dta/i18n/es_PE.po
odoo_addons/l10n_ch_dta/i18n/es_VE.po
odoo_addons/l10n_ch_dta/i18n/et.po
odoo_addons/l10n_ch_dta/i18n/eu.po
odoo_addons/l10n_ch_dta/i18n/fa.po
odoo_addons/l10n_ch_dta/i18n/fi.po
odoo_addons/l10n_ch_dta/i18n/fr.po
odoo_addons/l10n_ch_dta/i18n/fr_CA.po
odoo_addons/l10n_ch_dta/i18n/fr_CH.po
odoo_addons/l10n_ch_dta/i18n/fr_FR.po
odoo_addons/l10n_ch_dta/i18n/gl.po
odoo_addons/l10n_ch_dta/i18n/gl_ES.po
odoo_addons/l10n_ch_dta/i18n/he.po
odoo_addons/l10n_ch_dta/i18n/hi.po
odoo_addons/l10n_ch_dta/i18n/hr.po
odoo_addons/l10n_ch_dta/i18n/hr_HR.po
odoo_addons/l10n_ch_dta/i18n/hu.po
odoo_addons/l10n_ch_dta/i18n/id.po
odoo_addons/l10n_ch_dta/i18n/it.po
odoo_addons/l10n_ch_dta/i18n/ja.po
odoo_addons/l10n_ch_dta/i18n/ko.po
odoo_addons/l10n_ch_dta/i18n/lo.po
odoo_addons/l10n_ch_dta/i18n/lt.po
odoo_addons/l10n_ch_dta/i18n/lt_LT.po
odoo_addons/l10n_ch_dta/i18n/lv.po
